{
  "Operation:default": {
    "fields": {
      "fixMe": {
        "inputType": "input"
      }
    }
  },
  "Find:default": {
    "fields": {
      "storagePlace": {
        "inputType": "radio"
      },
      "measuringPointID": {
        "inputType": "input"
      },
      "measuringPointOrigin": {
        "inputType": "radio"
      },
      "workflow": {
        "inputType": "checkboxes"
      },
      "MasseSonstige": {
        "inputType": "input"
      },
      "MasseFixMe": {
        "inputType": "input"
      },
      "fixMe": {
        "inputType": "input"
      }
    },
    "valuelists": {
      "storagePlace": "Find-storagePlace-kalapodi",
      "measuringPointOrigin": "Find-measuringPointOrigin-kalapodi",
      "workflow": "Find-workflow-kalapodi",
      "period": "periods-kalapodi-1"
    }
  },
  "Sample:default": {
    "color": "#cef500",
    "hidden": ["weight"],
    "fields": {
      "descriptionSample": {
        "inputType": "text"
      },
      "researchQuestion": {
        "inputType": "text"
      },
      "analyzedBy": {
        "inputType": "input"
      },
      "sampleRelatedTo": {
        "inputType": "input"
      },
      "comment": {
        "inputType": "input"
      },
      "sampleState": {
        "inputType": "radio"
      }
    },
    "valuelists": {
      "sampleType": "Sample-sampleType-Campidoglio",
      "sampleState": "Sample-sampleState-Campidoglio"
    }
  },
  "Feature:default": {
    "fields": {
      "if1Befundart": {
        "inputType": "input"
      },
      "if1SchichtKuenstlichNatuerlich": {
        "inputType": "input"
      },
      "if1AutoKlassifizierungOhneBefundart": {
        "inputType": "input"
      },
      "if1SchichtPartikel": {
        "inputType": "input"
      },
      "if1SchichtBrocken": {
        "inputType": "input"
      },
      "if1SchichtBroeckchen": {
        "inputType": "input"
      },
      "if1SchichtMaxGroesze": {
        "inputType": "input"
      },
      "if1SchichtKonsistenz": {
        "inputType": "input"
      },
      "if1SchichtBesondereBeobachtungen": {
        "inputType": "input"
      },
      "if1SchichtFormat": {
        "inputType": "input"
      },
      "if1SchichtKlassifizSonst": {
        "inputType": "input"
      },
      "if1MasseSonstige": {
        "inputType": "input"
      },
      "fixMe": {
        "inputType": "input"
      }
    }
  },
  "Image:default": {
    "fields": {
      "fixMe": {
        "inputType": "input"
      }
    }
  },
  "Photo:default": {
    "commons": ["date"],
    "fields": {
      "imageSubject": {
        "inputType": "radio"
      },
      "originalType": {
        "inputType": "dropdown"
      }
    },
    "valuelists": {
      "imageSubject": "Photo-imageSubject-kalapodi",
      "originalType": "Photo-originalType-default"
    }
  },
  "Drawing:default": {
    "commons": ["date"],
    "fields": {
      "imageSubject": {
        "inputType": "radio"
      },
      "drawingType": {
        "inputType": "radio"
      },
      "if1ZeichnungsGegenstand": {
        "inputType": "input"
      }
    },
    "valuelists": {
      "imageSubject": "Photo-imageSubject-kalapodi",
      "drawingType":  "Drawing-drawingType-kalapodi"
    }
  },
  "Metal:default": {
    "fields": {
      "objectTypeGeneral": {
        "inputType": "dropdown"
      },
      "objectType": {
        "inputType": "dropdown"
      },
      "objectTypeSpecific": {
        "inputType": "input"
      },
      "formDescription": {
        "inputType": "checkboxes"
      },
      "metalMaterial": {
        "inputType": "checkboxes"
      }
    },
    "valuelists": {
      "objectTypeGeneral": "Metal-objectTypeGeneral-kalapodi",
      "objectType": "Metal-objectType-kalapodi",
      "formDescription": "Metal-formDescription-kalapodi",
      "metalMaterial": "Metal-metalMaterial-kalapodi"
    }
  },
  "Coin:default": {
    "fields": {
      "metalMaterial": {
        "inputType": "checkboxes"
      },
      "mint": {
        "inputType": "dropdown"
      }
    },
    "valuelists": {
      "metalMaterial": "Coin-metalMaterial-kalapodi",
      "mint": "Coin-mint-kalapodi"
    }
  },
  "Brick:default": {
    "fields": {
      "if1Verwendung": {
        "inputType": "input"
      },
      "brickUsage": {
        "inputType": "radio"
      }
    },
    "valuelists": {
      "brickUsage": "Brick-brickUsage-kalapodi"
    }
  },
  "PlasterFragment:default": {
    "fields": {
      "if1Klassifizierung": {
        "inputType": "input"
      }
    }
  },
  "Planum": {
    "color": "#cef500",
    "parent": "Feature",
    "fields": {
      "objectOrigin": {
        "inputType": "radio"
      },
      "if1TiefeRelativ": {
        "inputType": "input"
      }
    },
    "valuelists": {
      "objectOrigin": "Find-measuringPointOrigin-kalapodi"
    }
  },
  "BrickCluster": {
    "color": "#cef500",
    "parent": "Find",
    "fields": {}
  },
  "Pottery:default": {
    "fields": {
      "materialType": {
        "inputType": "radio"
      },
      "if1Klassifizierung": {
        "inputType": "input"
      },
      "vesselFormSpecific": {
        "inputType": "dropdown"
      }
    },
    "valuelists": {
      "materialType": "Pottery-materialType-kalapodi",
      "vesselFormSpecific": "Pottery-vesselFormSpecific-kalapodi"
    }
  },
  "PotteryCluster": {
    "color": "#cef500",
    "parent": "Find",
    "fields": {}
  },
  "Layer:default": {
    "fields": {
      "if1Farbe2": {
        "inputType": "input"
      },
      "if1SchichtUnterscheidungsKrit": {
        "inputType": "input"
      },
      "if1SchichtEntstehung": {
        "inputType": "input"
      },
      "layerClassification": {
        "inputType": "dropdown"
      },
      "soilType": {
        "inputType": "dropdown"
      }
    },
    "valuelists": {
      "layerClassification": "Layer-layerClassification-kalapodi",
      "soilType": "Layer-soilType-kalapodi"
    }
  },
  "Project:default": {
    "hidden": [],
    "fields": {}
  },
  "Survey:default": {
    "hidden": [],
    "fields": {}
  },
  "SurveyUnit:default": {
    "hidden": [],
    "fields": {}
  },
  "Place:default": {
    "hidden": [],
    "fields": {}
  },
  "Area:default": {
    "hidden": [],
    "fields": {}
  },
  "Trench:default": {
    "hidden": [],
    "fields": {
      "researchQuestion": {
        "inputType": "text"
      }
    }
  },
  "Building:default": {
    "hidden": [],
    "fields": {}
  },
  "BuildingPart:default": {
    "hidden": [],
    "fields": {}
  },
  "Room:default": {
    "hidden": [],
    "fields": {}
  },
  "RoomCeiling:default": {
    "hidden": [],
    "fields": {}
  },
  "RoomFloor:default": {
    "hidden": [],
    "fields": {}
  },
  "RoomWall:default": {
    "hidden": [],
    "fields": {}
  },
  "Inscription:default": {
    "hidden": [],
    "fields": {}
  },
  "Glass:default": {
    "hidden": [],
    "fields": {}
  },
  "Mollusk:default": {
    "hidden": [],
    "fields": {}
  },
  "Burial:default": {
    "hidden": [],
    "fields": {}
  },
  "Wood:default": {
    "hidden": [],
    "fields": {}
  },
  "Architecture:default": {
    "hidden": [],
    "fields": {}
  },
  "Floor:default": {
    "hidden": [],
    "fields": {}
  },
  "Grave:default": {
    "hidden": [],
    "fields": {}
  },
  "Bone:default": {
    "hidden": [],
    "fields": {}
  },
  "Terracotta:default": {
    "hidden": [],
    "fields": {}
  },
  "Stone:default": {
    "hidden": [],
    "fields": {}
  },
  "Excavation:default": {
    "hidden": [],
    "fields": {}
  },
  "TypeCatalog:default": {
    "hidden": [],
    "fields": {}
  },
  "Type:default": {
    "hidden": [],
    "fields": {}
  }
}
