{
  "Feature": {
    "fields": {
      "stratigraphicReliability": {
        "inputType": "radio",
        "valuelist": [
          "gut",
          "nicht gut"
        ]
      },
      "color": {
        "inputType": "checkboxes",
        "valuelist": [
          "beige",
          "blass-",
          "blau",
          "braun",
          "cremefarben",
          "dunkel-",
          "gelb",
          "grau",
          "gräulich",
          "grün",
          "grünlich",
          "hell-",
          "leuchtend-",
          "ocker",
          "orange",
          "rosa",
          "rot",
          "schwarz",
          "türkis",
          "violett",
          "weiß",
          "ziegelrot"
        ]
      }
    }
  },
  "Layer": {
    "fields":{
      "layerClassification": {
        "inputType": "dropdown",
        "valuelist": [
          "Oberfläche",
          "Natürliche Ablagerung",
          "Künstliche Ablagerung",
          "Brandschicht",
          "Raumfüllung",
          "Kulturschicht",
          "Laufhorizont",
          "Planierschicht"
        ]
      },
      "distinguishingCriteria": {
        "inputType": "checkboxes",
        "valuelist": [
          "Farbe",
          "Form",
          "Grenzen",
          "Konsistenz",
          "Komposition"
        ]
      },
      "consistency": {
        "inputType": "checkboxes",
        "valuelist": [
          "Durch Brand versiegelt",
          "Oberfläche abgewaschen",
          "Oberfläche verhärtet",
          "aschig",
          "fest",
          "flüssig",
          "gut formbar",
          "hart",
          "humos",
          "lehmig",
          "locker",
          "mittel bindend",
          "mittel formbar",
          "nicht bindend",
          "nicht formbar",
          "porös",
          "sandig",
          "schwach bindend",
          "schwach formbar",
          "sehr gut formbar",
          "sehr hart",
          "sehr schwach formbar",
          "sehr weich",
          "stark bindend",
          "steif",
          "steinig",
          "weich"
        ]
      },
      "soilType": {
        "inputType": "dropdown",
        "valuelist": [
          "Çorak",
          "Feinsand",
          "Feinstsand",
          "Grobsand",
          "Lehm",
          "Lehmiger Sand",
          "Lehmiger Schluff",
          "Lehmiger Ton",
          "Mergel",
          "Mittlerer Sand",
          "Sand",
          "Sandiger Lehm",
          "Sandiger Schluff",
          "Sandiger Ton",
          "Schluff",
          "Schluffiger Lehm",
          "Schluffiger Sand",
          "Schluffiger Ton",
          "Ton",
          "Toniger Lehm",
          "Toniger Sand",
          "Toniger Schluff"
        ]
      }
    }
  },
  "Floor": {
    "fields":{
      "distinguishingCriteria": {
        "inputType": "checkboxes",
        "valuelist": [
          "Farbe",
          "Form",
          "Grenzen",
          "Konsistenz",
          "Komposition"
        ]
      },
      "floorClassification": {
        "inputType": "dropdown",
        "valuelist": [
          "Bastmatten",
          "Lehmboden",
          "Korkboden",
          "Mosaik",
          "Opus sectile",
          "Opus signinum",
          "Pflaster",
          "Stampflehm",
          "Terrazzo",
          "Webmatten",
          "Ziegel"
        ]
      }
    }
  },
  "Architecture": {
    "fields": {
      "architectureClassification": {
        "inputType": "radio",
        "valuelist": [
          "Architektur",
          "Versturz"
        ]
      },
      "construction": {
        "inputType": "dropdown",
        "valuelist": [
          "Bruchsteinmauer",
          "Felsbearbeitung",
          "Fundament: Geschüttet",
          "Fundament: gesetzt",
          "Kanal",
          "Mauerkern: Lesesteine",
          "einschalig vor Feld/Hang",
          "ohne Schalen/keine durchgehenden Lagen",
          "ohne Schalen/nur durchgehende Lagen",
          "zweischalig",
          "zweischalig mit Binderlagen"
        ]
      },
      "wallClassification": {
        "inputType": "dropdown",
        "valuelist": [
          "Apsis",
          "Aufgehendes",
          "Durchgang",
          "Fensterzusetzung",
          "Flickung",
          "Fundament",
          "Gewölbe",
          "Mauer",
          "Mauerbettung",
          "Mauerdurchbruch",
          "Mosaik",
          "Opus sectile",
          "Treppe",
          "Türzusetzung",
          "Wandgestaltung"
        ]
      },
      "wallType": {
        "inputType": "dropdown",
        "valuelist": [
          "Außenmauer",
          "Befestigugsmauer",
          "Blockmauerwerk",
          "Bruchsteinmauer",
          "Fachwerk",
          "Feldsteinmauer",
          "Grenzmauer",
          "Stadtmauer",
          "Poterne",
          "ungebrannte Lehmziegelmauer",
          "verbrannte Lehmziegelmauer",
          "Opus reticulatum",
          "Ziegelmauer"
        ]
      }
    }
  },
  "Find": {
    "fields": {
      "drawn": {
        "inputType": "radio",
        "valuelist": [
          "Ja",
          "Nein",
          "Nicht notwendig"
        ]
      },
      "photographed": {
        "inputType": "radio",
        "valuelist": [
          "Ja",
          "Nein",
          "Nicht notwendig"
        ]
      },
      "sketched": {
        "inputType": "radio",
        "valuelist": [
          "Ja",
          "Nein",
          "Nicht notwendig"
        ]
      },
      "storageInventoryNumberAdditional": {
        "inputType": "input"
      },
      "hasRestoration": {
        "inputType": "radio",
        "valuelist": [
          "Ja",
          "Nein",
          "Nicht notwendig"
        ]
      },
      "storagePlace": {
        "inputType": "radio",
        "valuelist": [
          "Museum Bogazköy",
          "Museum Çorum",
          "Depot",
          "Unbekannt"
        ]
      }
    }
  },
  "Bone": {
    "fields":{
      "boneClassification": {
        "inputType": "dropdown",
        "valuelist": [
          "Skelettfragmente",
          "Becken (Pelvis)",
          "Brustbein (Sternum)",
          "Elle (Ulna)",
          "Fingerknochen (Phalanges)",
          "Fußknochen",
          "Handknochen",
          "Kniescheibe (Patella)",
          "Langknochen",
          "Oberarm (Humerus)",
          "Oberschenkel (Femur)",
          "Rippen",
          "Schienenbein (Tibia)",
          "Schlüsselbein (Clavicula)",
          "Schulterblatt (Scapula)",
          "Schädel (Cranium)",
          "Speiche (Radius)",
          "Steißbein",
          "Undefinierbar",
          "Unterkiefer (Mandibula)",
          "Wadenbein (Fibula)",
          "Wirbel",
          "Zahn"
        ]
      },
      "treatment": {
        "inputType": "input"
      }
    }
  },
  "Brick": {
    "fields": {
      "brickForm": {
        "inputType": "checkboxes",
        "valuelist": [
          "Bodenziegel",
          "Dachziegel",
          "Flachziegel",
          "Formziegel",
          "Hypokaustziegel",
          "Imbrex",
          "Kalyptere",
          "Later",
          "Leistenziegel",
          "Lochziegel/Hohlziegel",
          "Stroter",
          "Tegula",
          "Wandziegel"
        ]
      },
      "specificType": {
        "inputType": "dropdown",
        "valuelist": [
          "Abschläge",
          "Berg",
          "Bodenziegel",
          "Bruchstein",
          "Dachziegel",
          "Geröll",
          "Hohlziegel",
          "Hypokaustziegel",
          "Kanalziegel",
          "Platten",
          "Quader",
          "Variierend",
          "Wandziegel",
          "Ziegelbruch"
        ]
      },
      "brickUsage": {
        "inputType": "radio",
        "valuelist": [
          "Dach",
          "Decke",
          "Fenster",
          "Fussboden",
          "Gewölbedecke",
          "Grab",
          "Klosterformat",
          "Türrahmen",
          "Türsturz",
          "Wand",
          "Wandverkleidung"
        ]
      },
      "manufacturingMethod": {
        "inputType": "radio",
        "valuelist": [
          "gedreht (auf Drehscheibe)",
          "gegossen",
          "gepresst",
          "gestrichen",
          "handgeformt"
        ]
      }
    }
  },
  "Stone": {
    "fields":{
      "color": {
        "inputType": "checkboxes",
        "valuelist": [
          "beige",
          "blass-",
          "blau",
          "braun",
          "cremefarben",
          "dunkel-",
          "gelb",
          "grau",
          "grün",
          "hell-",
          "leuchtend-",
          "ocker",
          "orange",
          "rosa",
          "rot",
          "schwarz",
          "türkis",
          "violett",
          "weiß",
          "-lich"
        ]
      },
      "objectType": {
        "inputType": "dropdown",
        "valuelist": [
          "Abschlag",
          "Altar",
          "Anhänger",
          "Architekturdekor",
          "Bauglied",
          "Becken",
          "Einlage",
          "Einsatzkopf",
          "Fußbodenfragment",
          "Gefäß",
          "Gerät",
          "Grabmarkierung",
          "Grabplatte",
          "Gussform",
          "Hammersteinfragment",
          "Herme",
          "Inkrustation",
          "Klopfstein",
          "Lampe",
          "Löffel",
          "Mahlstein",
          "Mobiliar",
          "Mörser",
          "Perle",
          "Plastik/Skulptur",
          "Produktionsfragment",
          "Reibstein",
          "Ring",
          "Rührstab",
          "Sarkophag",
          "Schlagstein",
          "Schmuck",
          "Siegel",
          "Spielbrett",
          "Spielstein",
          "Spinnwirtel",
          "Spolie",
          "Statuenbasis",
          "Stele",
          "Tessera",
          "Tischfuß",
          "Unsicher bzw. unbestimmbar",
          "Waffe",
          "Webgewicht",
          "Wetzstein",
          "Werkzeug",
          "Ölpresse"
        ]
      },
      "architectureElement": {
        "inputType": "dropdown",
        "valuelist": [
          "Akroter",
          "Architrav",
          "Archtitravfriesblock",
          "Basis",
          "Bauplastik",
          "Bodenplatte",
          "Fries",
          "Gesims",
          "Kapitell",
          "Konsole",
          "Leiste",
          "Profilstück",
          "Quaderblock",
          "Rinne",
          "Schrankenplatte",
          "Schwellenblock",
          "Sima",
          "Säule",
          "Wandverkleidung"
        ]
      },
      "origin": {
        "inputType": "dropdown",
        "valuelist": [
          "Alpen",
          "Anatolien",
          "Chimtou",
          "Harz",
          "Kreta",
          "Prokonnesos",
          "Sizilien",
          "Troas"
        ]
      }
    }
  },
  "PlasterFragment": {
    "fields": {
      "color": {
        "inputType": "checkboxes",
        "valuelist": [
          "beige",
          "blass-",
          "blau",
          "braun",
          "cremefarben",
          "dunkel-",
          "gelb",
          "grau",
          "grün",
          "hell-",
          "leuchtend-",
          "ocker",
          "orange",
          "rosa",
          "rot",
          "schwarz",
          "türkis",
          "violett",
          "weiß",
          "-lich"
        ]
      },
      "decorationColor": {
        "inputType": "input"
      },
      "decorationDescription": {
        "inputType": "input"
      }
    }
  },
  "Glass": {
    "fields": {
      "color": {
        "inputType": "checkboxes",
        "valuelist": [
          "beige",
          "blass-",
          "blau",
          "braun",
          "cremefarben",
          "dunkel-",
          "gelb",
          "grau",
          "grün",
          "hell-",
          "leuchtend-",
          "ocker",
          "orange",
          "rosa",
          "rot",
          "schwarz",
          "türkis",
          "violett",
          "weiß",
          "-lich"
        ]
      }
    }
  },
  "Pottery": {
    "fields": {
      "clayColorBreak": {
        "inputType": "checkboxes",
        "valuelist": [
          "beige",
          "blass-",
          "blau",
          "braun",
          "cremefarben",
          "dunkel-",
          "gelb",
          "grau",
          "grün",
          "hell-",
          "leuchtend-",
          "ocker",
          "orange",
          "rosa",
          "rot",
          "schwarz",
          "türkis",
          "violett",
          "weiß",
          "-lich"
        ]
      },
      "clayColorInside": {
        "inputType": "checkboxes",
        "valuelist": [
          "beige",
          "blass-",
          "blau",
          "braun",
          "cremefarben",
          "dunkel-",
          "gelb",
          "grau",
          "grün",
          "hell-",
          "leuchtend-",
          "ocker",
          "orange",
          "rosa",
          "rot",
          "schwarz",
          "türkis",
          "violett",
          "weiß",
          "-lich"
        ]
      },
      "clayColorOutside": {
        "inputType": "checkboxes",
        "valuelist": [
          "beige",
          "blass-",
          "blau",
          "braun",
          "cremefarben",
          "dunkel-",
          "gelb",
          "grau",
          "grün",
          "hell-",
          "leuchtend-",
          "ocker",
          "orange",
          "rosa",
          "rot",
          "schwarz",
          "türkis",
          "violett",
          "weiß",
          "-lich"
        ]
      },
      "specificType": {
        "inputType": "radio",
        "valuelist": [
          "Arretina schwarz",
          "Attisch farbig aufgehöhte Schwarzglanzton Ware",
          "Attische Keramik",
          "Attische Rotfigurige Keramik",
          "Attische Schwarzfigurige Keramik",
          "Attische Schwarzglanzton Ware",
          "Bemalte Keramik",
          "Bemalte Ware (floral)",
          "Bemalte Ware (linear)",
          "Bichrome Ware",
          "Campana A",
          "Campana B",
          "Campana B Imitation",
          "Campana B-oid",
          "Campana C",
          "Dünnwandige Feinkeramik",
          "Firnisware",
          "Glasierte Keramik",
          "Glattwandige Ware",
          "Hand",
          "Kappadokische Ware",
          "Korinthische Keramik",
          "Küchenware",
          "Monochrome Ware",
          "Ostgriechische Keramik",
          "Prähistorische Keramik",
          "Red Slip Ware",
          "Scheibenware",
          "Schlichte Ware",
          "Schwarzglanzton Ware",
          "Terra sigilata",
          "Tongrundige Ware"
        ]
      },
      "objectType": {
        "inputType": "dropdown",
        "valuelist": [
          "Altar",
          "Anhänger",
          "Antefix",
          "Becken",
          "Einlage",
          "Figurine (anthropomorph)",
          "Figurine (zoomorph)",
          "Gefäß",
          "Gerät",
          "Gussform",
          "Kette",
          "Kohlebecken",
          "Lampe",
          "Libationsgefäß",
          "Löffel",
          "Perle",
          "Plastik/Skulptur",
          "Produktionsfragment",
          "Ring",
          "Sarkophag",
          "Schmuck",
          "Siegel",
          "Spielstein",
          "Spinnwirtel",
          "Tonrohr",
          "Unsicher bzw. unbestimmbar",
          "Webgewicht",
          "Werkzeug"
        ]
      },
      "vesselForm": {
        "inputType": "dropdown",
        "valuelist": [
          "Amphore",
          "Aschenurne",
          "Becher",
          "Becken",
          "Deckel",
          "Deckelgefäß",
          "Dinos",
          "Flasche",
          "Geschlossenes Gefäß",
          "Kanne",
          "Kasserole",
          "Kochschüssel",
          "Krater",
          "Krug",
          "Napf",
          "Offenes Gefäß",
          "Pithos",
          "Pfanne",
          "Pyxis",
          "Räuchergefäß",
          "Schale",
          "Schüssel",
          "Tasse",
          "Teller",
          "Teller/Untersatz",
          "Topf",
          "Unbestimmt",
          "Vase",
          "Vorratsgefäß"
        ]
      }
    }
  },
  "Sample": {
    "parent" : "Find",
    "commons": ["processor", "date","description", "dating", "dimensionLength", "dimensionWidth", "dimensionVerticalExtent", "spatialLocation"],
    "color": "#9ecae1",
    "fields": {
      "labNumber": {
        "inputType": "input"
      },
      "weight": {
        "inputType": "unsignedFloat"
      },
      "sampleType": {
        "inputType": "radio",
        "valuelist": [
          "Boden",
          "C14",
          "Holzkohle",
          "Hammerschlag",
          "Mörtel",
          "Lehmziegel"
        ]
      },
      "soilType": {
        "inputType": "dropdown",
        "valuelist": [
          "Çorak",
          "Feinsand",
          "Feinstsand",
          "Grobsand",
          "Lehm",
          "Lehmiger Sand",
          "Lehmiger Schluff",
          "Lehmiger Ton",
          "Mergel",
          "Mittlerer Sand",
          "Sand",
          "Sandiger Lehm",
          "Sandiger Schluff",
          "Sandiger Ton",
          "Schluff",
          "Schluffiger Lehm",
          "Schluffiger Sand",
          "Schluffiger Ton",
          "Ton",
          "Toniger Lehm",
          "Toniger Sand",
          "Toniger Schluff"
        ]
      },
      "comment": {
        "inputType": "input"
      }
    }
  },
  "Mollusk": {
    "fields": {
      "treatment": {
        "inputType": "input"
      },
      "classification": {
        "inputType": "input"
      }
    }
  },
  "Wood": {
    "fields": {
      "objectType": {
        "inputType": "dropdown",
        "valuelist": [
          "Altar",
          "Anhänger",
          "Architekturrest",
          "Gefäß",
          "Gerät",
          "Grabmarkierung",
          "Grabplatte",
          "Gussform",
          "Kasten/Kiste",
          "Löffel",
          "Mobiliar",
          "Plastik/Skulptur",
          "Ring",
          "Sarkophag",
          "Schmuck",
          "Unsicher bzw. unbestimmbar"
        ]
      }
    }
  },
  "Coin": {
    "fields": {
      "mintingRuler": {
        "inputType": "dropdown",
        "valuelist": [
          "Arcadius",
          "Caracalla",
          "Constans",
          "Constans I.",
          "Constantius II.",
          "Domitian",
          "Hadrian",
          "Konstantin II.",
          "Nero",
          "Konstantin",
          "Licinius",
          "Maximinian",
          "Myrina",
          "Septimius Severus",
          "Traian",
          "Türkische Republik",
          "Valentianus III"
        ]
      },
      "mint": {
        "inputType": "dropdown",
        "valuelist": [
          "Abdera",
          "Abydos",
          "Afrika",
          "Agrigent",
          "Aigai (Vergina)",
          "Aiolis",
          "Aitolischer Bund",
          "Akanthus",
          "Akkon",
          "Alabanda",
          "Alexandria",
          "Alexandria Troas",
          "Alexandrien",
          "Amasra",
          "Amathus",
          "Ambianum (Amiens)",
          "Ambracia",
          "Amiens",
          "Amisus",
          "Amphipolis",
          "Amrit",
          "Anaktorio",
          "Antiochia",
          "Antiochia (Antakya)",
          "Antiochia am Orontes",
          "Ancyra",
          "Apameia Kibotos",
          "Apameia am Orontes",
          "Apollonia",
          "Apulien",
          "Aquileia",
          "Archaiischer Bund",
          "Arelate (Arles)",
          "Argos",
          "Argos Amphilochicum",
          "Arles",
          "Arpi",
          "Aruad",
          "Asia Minor",
          "Asien",
          "Aspendos",
          "Assos",
          "Astibus",
          "Athen",
          "Aydın",
          "Babylon",
          "Barcino (Barcelona)",
          "Beirut",
          "Bozcaada",
          "Byblos",
          "Byzantion",
          "Böotien",
          "Caesaraugusta",
          "Caesarea in Kappadokien",
          "Cales",
          "Camulodunum (Colchester)",
          "Canosa di Puglia",
          "Carnuntum",
          "Carthago (Tunis)",
          "Catania",
          "Caulonia",
          "Chalcedon",
          "Chalkida",
          "Chalkidiki",
          "Chersones",
          "Chios",
          "Colchester",
          "Colonia Agrippina (Köln)",
          "Colonia Patricia",
          "Comitatenses",
          "Constantinopolis (Istanbul)",
          "Crotone",
          "Cyme",
          "Damaskus",
          "Diesseitiges Gallian / Norditalien",
          "Dionysopolis",
          "Dyrrhachium",
          "Ekbatana",
          "Elea",
          "Elis",
          "Emerita",
          "Empüries",
          "Ephesos",
          "Eretria",
          "Erythrai",
          "Etrurien",
          "Euböa",
          "Foça",
          "Gallien",
          "Gela",
          "Germe",
          "Gortyn",
          "Halikarnassos",
          "Harran",
          "Heraclea",
          "Herakleia",
          "Herakleia Pontike",
          "Himera",
          "Hispanien",
          "Hispanien-Punisch",
          "Histria",
          "Homs",
          "Ibiza",
          "Idalion",
          "Italien",
          "Italien (Südosten)",
          "Kabile",
          "Kamarina",
          "Karien",
          "Karthago",
          "Karystos",
          "Kelenderis",
          "Kertsch",
          "Klazomenai",
          "Knidos",
          "Kolchis",
          "Kolophon",
          "Konstantinopel",
          "Korfu",
          "Korinth",
          "Korinthischer Bund",
          "Kos",
          "Kydonia",
          "Kyrenaika",
          "Kyrene",
          "Kyzikos",
          "Köln",
          "Lampsakos",
          "Laodikeia am Lykos",
          "Lapta",
          "Larissa",
          "Larnaka",
          "Latakia",
          "Lefkada",
          "Lentini",
          "Lete",
          "Locri",
          "Locri Opuntii (Opus)",
          "Londinium",
          "Lucera",
          "Lugdunum",
          "Lydien",
          "Lykien",
          "Lysimacheia",
          "Lyttos",
          "Magnesia am Mäander",
          "Mainz",
          "Makedonien",
          "Makedonien (1. Region)",
          "Mangalia",
          "Marmetini",
          "Maroneia",
          "Marseille",
          "Mediolanum",
          "Megalopoli",
          "Memphis",
          "Messene",
          "Messina",
          "Metapont",
          "Milas",
          "Milet",
          "Mithymna",
          "Mittelitalien",
          "Myriandrus",
          "Myrina",
          "Mytilini",
          "Narbo",
          "Naxos",
          "Neapel",
          "Nessebar",
          "Nikomedia",
          "Nisibis",
          "Nuceria",
          "Olbia",
          "Oreus",
          "Oria",
          "Ostia Antica",
          "Ouranoupolis",
          "Paestum",
          "Paphos",
          "Parion",
          "Paros",
          "Pella",
          "Peloponnes",
          "Pergamon",
          "Perge",
          "Persien",
          "Phanagoria",
          "Phaselis",
          "Phokis",
          "Priene",
          "Prusias ad Hypium",
          "Ravenna",
          "Reggio Calabria",
          "Republik Zypern",
          "Rhodos",
          "Rom",
          "Rouen",
          "Salamis",
          "Samos",
          "Sardes",
          "Sardinien",
          "Segesta",
          "Seleukia Pieria",
          "Seleukia am Tigris",
          "Selinus",
          "Sestos",
          "Side",
          "Sidon",
          "Sikyon",
          "Sinop",
          "Sirmium",
          "Sisak",
          "Sizilien",
          "Sizilien 2 (Republican period)",
          "Sizilisch-Punisch",
          "Smyrna",
          "Sofia",
          "Soloi",
          "Sosopol",
          "Susa (Persien)",
          "Sybaris",
          "Syrakus",
          "Syrien",
          "Südgallische Münzstätte",
          "Tanagra",
          "Taras",
          "Tarraco",
          "Tarsus",
          "Tavium",
          "Tegea",
          "Temnus",
          "Teos",
          "Terina",
          "Tessin",
          "Thasos",
          "Thessalische Liga",
          "Thessalonica",
          "Thessaloniki",
          "Thiva",
          "Thrakien",
          "Thurioi",
          "Thyrrheium",
          "Trier",
          "Tripoli (Libanon)",
          "Tyros",
          "Unsicher bzw. unbestimmbar",
          "Viminatium",
          "Vindobona",
          "Warna",
          "Zancle",
          "Äegina",
          "Äeneas",
          "Äetolien"
        ]
      }
    }
  },
  "Inscription": {
    "fields": {
      "objectType": {
        "inputType": "checkboxes",
        "valuelist": [
          "Bulle",
          "Beschriftete Gegenstände",
          "Beschriftete Waffen",
          "Alltäglicher Gebrauch",
          "Bauinschrift",
          "Ehreninschrift",
          "Felsinschrift",
          "Grabinschrift (Inschrift im Grabkontext)",
          "Öffentliche Ausstattung",
          "Private Ausstattung",
          "Sakrale Ausstattung",
          "Siegel",
          "Siegelabdruck",
          "Tontafel",
          "Urkunde",
          "Wasserversorgung",
          "Weihinschrift",
          "Unsicher bzw. unbestimmbar"
        ]
      }
    }
  }
}
